cryptography/__about__.py
cryptography/__init__.py
cryptography/exceptions.py
cryptography/fernet.py
cryptography/py.typed
cryptography/utils.py
cryptography/hazmat/__init__.py
cryptography/hazmat/_oid.py
cryptography/hazmat/backends/__init__.py
cryptography/hazmat/backends/openssl/__init__.py
cryptography/hazmat/backends/openssl/backend.py
cryptography/hazmat/bindings/__init__.py
cryptography/hazmat/bindings/_rust.abi3.so
cryptography/hazmat/bindings/_rust/__init__.pyi
cryptography/hazmat/bindings/_rust/_openssl.pyi
cryptography/hazmat/bindings/_rust/asn1.pyi
cryptography/hazmat/bindings/_rust/exceptions.pyi
cryptography/hazmat/bindings/_rust/ocsp.pyi
cryptography/hazmat/bindings/_rust/pkcs12.pyi
cryptography/hazmat/bindings/_rust/pkcs7.pyi
cryptography/hazmat/bindings/_rust/test_support.pyi
cryptography/hazmat/bindings/_rust/x509.pyi
cryptography/hazmat/bindings/_rust/openssl/__init__.pyi
cryptography/hazmat/bindings/_rust/openssl/aead.pyi
cryptography/hazmat/bindings/_rust/openssl/ciphers.pyi
cryptography/hazmat/bindings/_rust/openssl/cmac.pyi
cryptography/hazmat/bindings/_rust/openssl/dh.pyi
cryptography/hazmat/bindings/_rust/openssl/dsa.pyi
cryptography/hazmat/bindings/_rust/openssl/ec.pyi
cryptography/hazmat/bindings/_rust/openssl/ed25519.pyi
cryptography/hazmat/bindings/_rust/openssl/ed448.pyi
cryptography/hazmat/bindings/_rust/openssl/hashes.pyi
cryptography/hazmat/bindings/_rust/openssl/hmac.pyi
cryptography/hazmat/bindings/_rust/openssl/kdf.pyi
cryptography/hazmat/bindings/_rust/openssl/keys.pyi
cryptography/hazmat/bindings/_rust/openssl/poly1305.pyi
cryptography/hazmat/bindings/_rust/openssl/rsa.pyi
cryptography/hazmat/bindings/_rust/openssl/x25519.pyi
cryptography/hazmat/bindings/_rust/openssl/x448.pyi
cryptography/hazmat/bindings/openssl/__init__.py
cryptography/hazmat/bindings/openssl/_conditional.py
cryptography/hazmat/bindings/openssl/binding.py
cryptography/hazmat/decrepit/__init__.py
cryptography/hazmat/decrepit/ciphers/__init__.py
cryptography_qpython-44.0.0.dist-info/METADATA
cryptography_qpython-44.0.0.dist-info/WHEEL
cryptography_qpython-44.0.0.dist-info/top_level.txt
cryptography_qpython-44.0.0.dist-info/RECORD
